blackbox_decoder/__init__.py
blackbox_decoder/__main__.py
blackbox_decoder/app.py
blackbox_decoder/log.py
blackbox_decoder/main.py
blackbox_decoder/parse.py
blackbox_decoder-0.3.0.dist-info/METADATA
blackbox_decoder-0.3.0.dist-info/WHEEL
blackbox_decoder-0.3.0.dist-info/entry_points.txt
blackbox_decoder-0.3.0.dist-info/RECORD
