Metadata-Version: 2.1
Name: blackbox-decoder
Version: 0.3.0
Summary: The blackbox is a loggging system used within our autonomous drone system. The decoder is a tool to help decode the logs from their hex format into a human readable format.
Author: Cole Rottenberg
Author-email: Cole.rottenberg@gmail.com
Requires-Python: >=3.10,<4.0
Classifier: Programming Language :: Python :: 3
Classifier: Programming Language :: Python :: 3.10
Classifier: Programming Language :: Python :: 3.11
Classifier: Programming Language :: Python :: 3.12
Provides-Extra: dev
Requires-Dist: bitstring (>=4.2.3,<5.0.0)
Requires-Dist: matplotlib (>=3.9.1,<4.0.0)
Requires-Dist: pandas (>=2.2.2,<3.0.0)
Requires-Dist: pyqt6 (>=6.7.1,<7.0.0)
